quark_plugin_tsp/__init__.py
quark_plugin_tsp/classical_tsp_solver.py
quark_plugin_tsp/tsp_graph_provider.py
quark_plugin_tsp/tsp_qubo_mapping.py
quark_plugin_tsp-2.4.1.dist-info/licenses/LICENSE
quark_plugin_tsp-2.4.1.dist-info/licenses/NOTICE
quark_plugin_tsp-2.4.1.dist-info/METADATA
quark_plugin_tsp-2.4.1.dist-info/WHEEL
quark_plugin_tsp-2.4.1.dist-info/top_level.txt
quark_plugin_tsp-2.4.1.dist-info/RECORD
